kalibrate/__init__.py
kalibrate/fn.py
kalibrate/kalibrate.py
kalibrate/sanity.py
kalibrate-1.1.2.dist-info/DESCRIPTION.rst
kalibrate-1.1.2.dist-info/METADATA
kalibrate-1.1.2.dist-info/RECORD
kalibrate-1.1.2.dist-info/WHEEL
kalibrate-1.1.2.dist-info/metadata.json
kalibrate-1.1.2.dist-info/top_level.txt
