Metadata-Version: 2.0
Name: kalibrate
Version: 1.1.2
Summary: A python wrapper for kalibrate-rtl
Home-page: https://github.com/ashmastaflash/kal-wrapper
Author: Ash Wilson
Author-email: ash.d.wilson@gmail.com
License: BSD
Keywords: kalibrate kal rtl-sdr sdr
Platform: UNKNOWN
